calling_rate/__init__.py
calling_rate/cli.py
calling_rate/curator.py
calling_rate/number_of_burrows_from_call_rates.py
calling_rate/raw_data_to_tdp.py
calling_rate-0.5.0.dist-info/entry_points.txt
calling_rate-0.5.0.dist-info/LICENSE
calling_rate-0.5.0.dist-info/WHEEL
calling_rate-0.5.0.dist-info/METADATA
calling_rate-0.5.0.dist-info/RECORD
