Metadata-Version: 2.1
Name: calling_rate
Version: 0.5.0
Summary: Calculate population size from calling rate of seabirds
Home-page: https://github.com/IslasGECI/calling_rate
Author: Ciencia de Datos • GECI
Author-email: ciencia.datos@islas.org.mx
Requires-Python: >=3.9
Classifier: License :: OSI Approved :: GNU General Public License v3 or later (GPLv3+)
Requires-Dist: geopandas
Requires-Dist: matplotlib
Requires-Dist: pandas-stubs
Requires-Dist: pandas
Requires-Dist: scipy
Requires-Dist: typer[all]
Requires-Dist: utm
